beast_mailbox_core/__init__.py
beast_mailbox_core/cli.py
beast_mailbox_core/redis_mailbox.py
beast_mailbox_core-0.3.1.dist-info/licenses/LICENSE
beast_mailbox_core-0.3.1.dist-info/METADATA
beast_mailbox_core-0.3.1.dist-info/WHEEL
beast_mailbox_core-0.3.1.dist-info/entry_points.txt
beast_mailbox_core-0.3.1.dist-info/top_level.txt
beast_mailbox_core-0.3.1.dist-info/RECORD
