Metadata-Version: 2.4
Name: beast-mailbox-core
Version: 0.3.1
Summary: Redis-backed mailbox utilities from Beast Mode
License: MIT
Project-URL: Homepage, https://github.com/nkllon/beast-mailbox-core
Project-URL: Repository, https://github.com/nkllon/beast-mailbox-core
Keywords: redis,messaging,mailbox,async,streams
Classifier: Development Status :: 4 - Beta
Classifier: Intended Audience :: Developers
Classifier: License :: OSI Approved :: MIT License
Classifier: Programming Language :: Python :: 3
Classifier: Programming Language :: Python :: 3.9
Classifier: Programming Language :: Python :: 3.10
Classifier: Programming Language :: Python :: 3.11
Classifier: Programming Language :: Python :: 3.12
Classifier: Topic :: Software Development :: Libraries :: Python Modules
Classifier: Topic :: System :: Distributed Computing
Requires-Python: >=3.9
License-File: LICENSE
Requires-Dist: redis>=5.0.0
Provides-Extra: dev
Requires-Dist: pytest>=7.0.0; extra == "dev"
Requires-Dist: pytest-asyncio>=0.21.0; extra == "dev"
Requires-Dist: pytest-cov>=4.0.0; extra == "dev"
Dynamic: license-file
